[{"topTop":"5G 新品","url":"images/hot/h_1.png","name":"荣耀V30 PRO","discount":"享6期免息","price":"￥4199"},{"topTop":"爆款","url":"images/hot/h_2.png","name":"HUAWEI nova 5z","discount":"限时直降200","price":"￥1399"},{"topTop":"","url":"images/hot/h_3.png","name":"荣耀20","discount":"最高优惠600","price":"￥2099"},{"topTop":"免息","url":"images/hot/h_4.png","name":"HUAWEI Mate 30 4G","discount":"享12期免息","price":"4299"},{"topTop":"","url":"images/hot/h_5.png","name":"荣耀V20","discount":"最高优惠500","price":"￥1899"},{"topTop":"5G新品","url":"images/hot/h_6.png","name":"HUAWEI nova 6","discount":"12期免息","price":"￥3799"},{"topTop":"","url":"images/hot/h_7.png","name":"荣耀20i","discount":"最高将500","price":"￥1099"},{"topTop":"","url":"images/hot/h_8.png","name":"HUAWEI P30","discount":"赠好礼|享6期免息","price":"￥3688"}]